Metadata-Version: 1.0
Name: django-memcached-pool
Version: 0.5
Summary: A Memcached Pool for Django
Home-page: https://github.com/mozilla/django-memcached-pool
Author: Mozilla Services
Author-email: services-dev@mozilla.org
License: UNKNOWN
Keywords: django memcached pool
Platform: UNKNOWN
Classifier: Programming Language :: Python
Classifier: Framework :: Pylons
Classifier: Topic :: Internet :: WWW/HTTP
Classifier: Topic :: Internet :: WWW/HTTP :: WSGI :: Application
Classifier: License :: OSI Approved :: Apache Software License
